atomneb/__init__.py
atomneb/atomneb.py
atomneb/version.py
atomneb-0.3.4.data/data/LICENSE
atomneb-0.3.4.dist-info/AUTHORS.rst
atomneb-0.3.4.dist-info/LICENSE
atomneb-0.3.4.dist-info/METADATA
atomneb-0.3.4.dist-info/WHEEL
atomneb-0.3.4.dist-info/top_level.txt
atomneb-0.3.4.dist-info/RECORD
