Metadata-Version: 2.1
Name: atomneb
Version: 0.3.4
Summary: atomneb: Python Package for Atomic Data of Ionized Nebulae
Home-page: https://atomneb.github.io/AtomNeb-py/
Download-URL: https://github.com/atomneb/AtomNeb-py
Author: Ashkbiz Danehkar
Author-email: ashkbiz.danehkar@students.mq.edu.au
License: http://www.gnu.org/licenses/gpl.html
Keywords: atomneb,Chianti atomic database,atomic datasets,recombination lines,collisionally excited lines,recombination coefficients
Platform: any
License-File: LICENSE
License-File: AUTHORS.rst
Requires-Dist: numpy
Requires-Dist: astropy
